{
  "data": {
    "article": {},
    "attachments": {},
    "author_id": "2008589299659481088",
    "conversation_id": "2038582120000721120",
    "created_at": "2026-03-30T11:40:27.000Z",
    "edit_controls": {
      "editable_until": "2026-03-30T12:40:27.000Z",
      "edits_remaining": 5,
      "is_edit_eligible": false
    },
    "edit_history_tweet_ids": [
      "2038582120000721120"
    ],
    "entities": {
      "mentions": [
        {
          "end": 15,
          "id": "1829229897195368455",
          "start": 3,
          "username": "OVOTVTOVO_3"
        }
      ]
    },
    "geo": {},
    "id": "2038582120000721120",
    "lang": "zh",
    "note_tweet": {
      "entities": {}
    },
    "possibly_sensitive": false,
    "public_metrics": {
      "bookmark_count": 0,
      "impression_count": 0,
      "like_count": 0,
      "quote_count": 0,
      "reply_count": 0,
      "retweet_count": 45
    },
    "referenced_tweets": [
      {
        "id": "2038281436856566238",
        "type": "retweeted"
      }
    ],
    "reply_settings": "everyone",
    "text": "RT @OVOTVTOVO_3: 我想问一下穷逼这个圈子怎么退呀"
  },
  "includes": {
    "tweets": [
      {
        "article": {},
        "attachments": {},
        "author_id": "2008589299659481088",
        "conversation_id": "2038582120000721120",
        "created_at": "2026-03-30T11:40:27.000Z",
        "edit_controls": {
          "editable_until": "2026-03-30T12:40:27.000Z",
          "edits_remaining": 5,
          "is_edit_eligible": false
        },
        "edit_history_tweet_ids": [
          "2038582120000721120"
        ],
        "entities": {
          "mentions": [
            {
              "end": 15,
              "id": "1829229897195368455",
              "start": 3,
              "username": "OVOTVTOVO_3"
            }
          ]
        },
        "geo": {},
        "id": "2038582120000721120",
        "lang": "zh",
        "note_tweet": {
          "entities": {}
        },
        "possibly_sensitive": false,
        "public_metrics": {
          "bookmark_count": 0,
          "impression_count": 0,
          "like_count": 0,
          "quote_count": 0,
          "reply_count": 0,
          "retweet_count": 45
        },
        "referenced_tweets": [
          {
            "id": "2038281436856566238",
            "type": "retweeted"
          }
        ],
        "reply_settings": "everyone",
        "text": "RT @OVOTVTOVO_3: 我想问一下穷逼这个圈子怎么退呀"
      },
      {
        "article": {},
        "attachments": {},
        "author_id": "1829229897195368455",
        "conversation_id": "2038281436856566238",
        "created_at": "2026-03-29T15:45:38.000Z",
        "edit_controls": {
          "editable_until": "2026-03-29T16:45:38.000Z",
          "edits_remaining": 5,
          "is_edit_eligible": true
        },
        "edit_history_tweet_ids": [
          "2038281436856566238"
        ],
        "entities": {},
        "geo": {},
        "id": "2038281436856566238",
        "lang": "zh",
        "note_tweet": {
          "entities": {}
        },
        "possibly_sensitive": false,
        "public_metrics": {
          "bookmark_count": 0,
          "impression_count": 7437,
          "like_count": 212,
          "quote_count": 2,
          "reply_count": 29,
          "retweet_count": 45
        },
        "reply_settings": "everyone",
        "text": "我想问一下穷逼这个圈子怎么退呀"
      }
    ],
    "users": [
      {
        "created_at": "2026-01-06T17:19:51.000Z",
        "description": "喜欢我就多给我点钱让我生活更好",
        "id": "2008589299659481088",
        "name": "人类",
        "profile_image_url": "https://pbs.twimg.com/profile_images/2036846368636153856/rXAdJUpF_normal.jpg",
        "protected": false,
        "public_metrics": {
          "followers_count": 7,
          "following_count": 5,
          "like_count": 130,
          "listed_count": 0,
          "media_count": 5,
          "tweet_count": 50
        },
        "username": "TuT111500",
        "verified": false
      },
      {
        "created_at": "2024-08-29T18:49:42.000Z",
        "description": "？",
        "entities": {
          "url": {
            "urls": [
              {
                "display_url": "ngl.link/ovotvtouo",
                "end": 23,
                "expanded_url": "https://ngl.link/ovotvtouo",
                "start": 0,
                "url": "https://t.co/VHfQubyMuT"
              }
            ]
          }
        },
        "id": "1829229897195368455",
        "location": "提问箱",
        "name": "用户2778（祺嘉玛学长）",
        "pinned_tweet_id": "2008187932621123964",
        "profile_image_url": "https://pbs.twimg.com/profile_images/2032517620172468227/XWboBXgK_normal.jpg",
        "protected": false,
        "public_metrics": {
          "followers_count": 1322,
          "following_count": 67,
          "like_count": 2984,
          "listed_count": 1,
          "media_count": 243,
          "tweet_count": 4186
        },
        "url": "https://t.co/VHfQubyMuT",
        "username": "OVOTVTOVO_3",
        "verified": false
      }
    ]
  }
}